OpenPlatformShopeeAPI/Shopee.py
OpenPlatformShopeeAPI/__init__.py
OpenPlatformShopeeAPI-0.0.4.dist-info/LICENSE
OpenPlatformShopeeAPI-0.0.4.dist-info/METADATA
OpenPlatformShopeeAPI-0.0.4.dist-info/WHEEL
OpenPlatformShopeeAPI-0.0.4.dist-info/top_level.txt
OpenPlatformShopeeAPI-0.0.4.dist-info/RECORD
